dbbasic_cli/__init__.py
dbbasic_cli/cli.py
dbbasic_cli-1.0.0.dist-info/licenses/LICENSE
dbbasic_cli-1.0.0.dist-info/METADATA
dbbasic_cli-1.0.0.dist-info/WHEEL
dbbasic_cli-1.0.0.dist-info/entry_points.txt
dbbasic_cli-1.0.0.dist-info/top_level.txt
dbbasic_cli-1.0.0.dist-info/RECORD
