Metadata-Version: 2.4
Name: dbbasic-cli
Version: 1.0.0
Summary: Command-line tool for creating and managing DBBasic apps
Home-page: https://github.com/askrobots/dbbasic-cli-new
Author: DBBasic Project
Author-email: hello@dbbasic.com
Project-URL: Bug Reports, https://github.com/askrobots/dbbasic-cli-new/issues
Project-URL: Source, https://github.com/askrobots/dbbasic-cli-new
Project-URL: Documentation, http://dbbasic.com/cli-spec
Keywords: web framework cli database tsv dbbasic generator scaffold
Classifier: Development Status :: 4 - Beta
Classifier: Intended Audience :: Developers
Classifier: Topic :: Software Development :: Libraries :: Python Modules
Classifier: License :: OSI Approved :: MIT License
Classifier: Programming Language :: Python :: 3
Classifier: Programming Language :: Python :: 3.7
Classifier: Programming Language :: Python :: 3.8
Classifier: Programming Language :: Python :: 3.9
Classifier: Programming Language :: Python :: 3.10
Classifier: Programming Language :: Python :: 3.11
Classifier: Operating System :: OS Independent
Requires-Python: >=3.7
License-File: LICENSE
Dynamic: author
Dynamic: author-email
Dynamic: classifier
Dynamic: description
Dynamic: description-content-type
Dynamic: home-page
Dynamic: keywords
Dynamic: license-file
Dynamic: project-url
Dynamic: requires-python
Dynamic: summary
